tcmaker/__init__.py
tcmaker/solve.py
tcmaker/tcmaker.py
tcmaker/work.py
tcmaker-0.0.7.dist-info/METADATA
tcmaker-0.0.7.dist-info/WHEEL
tcmaker-0.0.7.dist-info/top_level.txt
tcmaker-0.0.7.dist-info/RECORD
